annie_lappd/__init__.py
annie_lappd/lappd.py
annie_lappd/plotlappd.py
annie_lappd-0.1.dist-info/METADATA
annie_lappd-0.1.dist-info/WHEEL
annie_lappd-0.1.dist-info/top_level.txt
annie_lappd-0.1.dist-info/RECORD
