Metadata-Version: 2.1
Name: annie_lappd
Version: 0.1
Summary: A package that processes the ASCII data generated by the ACDC boards.
Home-page: https://github.com/marvlad/annie_lappd/tree/main
Author: Marvin Ascencio-Sosa
Author-email: mascenci@fnal.gov
Classifier: Programming Language :: Python :: 3
Classifier: License :: OSI Approved :: MIT License
Classifier: Operating System :: OS Independent
Requires-Python: >=3.6
Requires-Dist: pandas>=1.0
Requires-Dist: numpy>=1.18
Requires-Dist: matplotlib>=3.0
Requires-Dist: tqdm>=4.0
